ros_numpy/__init__.py
ros_numpy/geometry.py
ros_numpy/image.py
ros_numpy/numpy_msg.py
ros_numpy/occupancy_grid.py
ros_numpy/point_cloud2.py
ros_numpy/registry.py
ros_numpy/transformations.py
rosnumpy-0.0.6.2.dist-info/LICENSE
rosnumpy-0.0.6.2.dist-info/METADATA
rosnumpy-0.0.6.2.dist-info/WHEEL
rosnumpy-0.0.6.2.dist-info/top_level.txt
rosnumpy-0.0.6.2.dist-info/RECORD
