Metadata-Version: 2.1
Name: rosnumpy
Version: 0.0.6.2
Summary: Tools for converting ROS messages to and from numpy arrays.
Author-email: manasrda <manasrda@mail.uc.edu>
Project-URL: Homepage, https://github.com/manasrda/ros_numpy
Project-URL: Bug Tracker, https://github.com/manasrda/ros_numpy/issues
Classifier: Programming Language :: Python :: 3
Classifier: License :: OSI Approved :: MIT License
Classifier: Operating System :: OS Independent
Requires-Python: >=3.6
License-File: LICENSE
Requires-Dist: numpy
Requires-Dist: genpy
Requires-Dist: bagpy ; sys_platform == "win32"
